{
  "Meta Data": {
    "1. Information": "Daily Prices (open, high, low, close) and Volumes",
    "2. Symbol": "TSLA",
    "3. Last Refreshed": "2025-03-27",
    "4. Output Size": "Compact",
    "5. Time Zone": "US/Eastern"
  },
  "Time Series (Daily)": {
    "2025-03-27": {
      "1. open": "272.4800",
      "2. high": "291.8500",
      "3. low": "271.8216",
      "4. close": "273.1300",
      "5. volume": "162572146"
    },
    "2025-03-26": {
      "1. open": "282.6600",
      "2. high": "284.9000",
      "3. low": "266.5100",
      "4. close": "272.0600",
      "5. volume": "156254441"
    },
    "2025-03-25": {
      "1. open": "283.6000",
      "2. high": "288.2000",
      "3. low": "271.2800",
      "4. close": "288.1400",
      "5. volume": "150361538"
    },
    "2025-03-24": {
      "1. open": "258.0750",
      "2. high": "278.6400",
      "3. low": "256.3300",
      "4. close": "278.3900",
      "5. volume": "169079865"
    },
    "2025-03-21": {
      "1. open": "234.9850",
      "2. high": "249.5200",
      "3. low": "234.5500",
      "4. close": "248.7100",
      "5. volume": "132728684"
    }
  }
}
